odoo/addons/base_facturx/README.rst
odoo/addons/base_facturx/__init__.py
odoo/addons/base_facturx/__manifest__.py
odoo/addons/base_facturx/i18n/base_facturx.pot
odoo/addons/base_facturx/i18n/base_zugferd.pot
odoo/addons/base_facturx/i18n/es.po
odoo/addons/base_facturx/i18n/fr.po
odoo/addons/base_facturx/i18n/it.po
odoo/addons/base_facturx/models/__init__.py
odoo/addons/base_facturx/models/base_facturx.py
odoo/addons/base_facturx/readme/CONFIGURE.md
odoo/addons/base_facturx/readme/CONTRIBUTORS.md
odoo/addons/base_facturx/readme/DESCRIPTION.md
odoo/addons/base_facturx/readme/USAGE.md
odoo/addons/base_facturx/static/description/icon.png
odoo/addons/base_facturx/static/description/index.html
odoo_addon_base_facturx-18.0.1.0.0.2.dist-info/METADATA
odoo_addon_base_facturx-18.0.1.0.0.2.dist-info/WHEEL
odoo_addon_base_facturx-18.0.1.0.0.2.dist-info/top_level.txt
odoo_addon_base_facturx-18.0.1.0.0.2.dist-info/RECORD
